github_context/__init__.py
github_context/github_context.py
github_context-0.3.1.dist-info/LICENSE
github_context-0.3.1.dist-info/METADATA
github_context-0.3.1.dist-info/WHEEL
github_context-0.3.1.dist-info/entry_points.txt
github_context-0.3.1.dist-info/top_level.txt
github_context-0.3.1.dist-info/RECORD
