Metadata-Version: 2.1
Name: github-context
Version: 0.3.1
Summary: A CLI tool to quickly extract context from GitHub repositories for AI
Home-page: https://github.com/elyxlz/github-context
Author: Elio Pascarelli
Author-email: elio@pascarelli.com
Classifier: Programming Language :: Python :: 3
Classifier: License :: OSI Approved :: MIT License
Classifier: Operating System :: POSIX :: Linux
Requires-Python: >=3.6
License-File: LICENSE
Requires-Dist: PyGithub
Requires-Dist: pyperclip
Requires-Dist: tqdm
